aiva_vrs/__init__.py
aiva_vrs/generator.py
aiva_vrs-0.1.0.dist-info/licenses/LICENSE
aiva_vrs-0.1.0.dist-info/METADATA
aiva_vrs-0.1.0.dist-info/WHEEL
aiva_vrs-0.1.0.dist-info/top_level.txt
aiva_vrs-0.1.0.dist-info/RECORD
