Metadata-Version: 2.4
Name: aiva-vrs
Version: 0.1.0
Summary: VRS Generator for mapping variants between different Variant Database Tables
Home-page: https://github.com/Mamidi-HealthTech-Solutions/aiva-vrs
Author: Mamidi HealthTech Solutions
Author-email: info@mamidi.co.in
Classifier: Programming Language :: Python :: 3
Classifier: License :: OSI Approved :: MIT License
Classifier: Operating System :: OS Independent
Classifier: Topic :: Scientific/Engineering :: Bio-Informatics
Classifier: Topic :: Scientific/Engineering :: Medical Science Apps.
Requires-Python: >=3.6
License-File: LICENSE
Dynamic: author
Dynamic: author-email
Dynamic: classifier
Dynamic: description
Dynamic: description-content-type
Dynamic: home-page
Dynamic: license-file
Dynamic: requires-python
Dynamic: summary
